[{"speaker1": "CHIEF", "speaker2": "COLLEGE BOY", "docId": 64, "answer_pos_tagged": ["VBZ", "NN", "JJ", "."], "qSentId": 0, "question": "This is it.", "question_pos_tagged": ["DT", "VBZ", "PRP", "."], "aSentId": 0, "answer": "Is something wrong?", "movie_name": "Feast.dial", "answer_ne_tagged": {}, "question_ne_tagged": {}}, {"speaker1": "CHIEF", "speaker2": "COLLEGE BOY", "docId": 64, "answer_pos_tagged": ["WP", "VBZ", "IN", "DT", "NN", "NN", "."], "qSentId": 1, "question": "Let's get that first barrel.", "question_pos_tagged": ["NNP", "POS", "NN", "IN", "JJ", "NN", "."], "aSentId": 1, "answer": "What's with the awkward silence?", "movie_name": "Feast.dial", "answer_ne_tagged": {}, "question_ne_tagged": {}}, {"speaker1": "CHIEF", "speaker2": "COLLEGE BOY", "docId": 64, "answer_pos_tagged": ["NNP", ":", ".", ".", "NNP", "."], "qSentId": 2, "question": "Last winter, a man kidnapped a little girl and holed up in one of these caves. The cops had him pinned down and began to move in. This guy started shooting... but he wasn't aiming at the officers... ...he was firing at something inside. When the dust cleared, all they found was the little girl's shoes. With the feet still in 'em.", "question_pos_tagged": ["JJ", "NN", ",", "DT", "NN", "VBD", "DT", "RB", "NN", "CC", "VBD", "RP", "IN", "CD", "IN", "DT", "NNP", "NNP", "NNS", "VBD", "PRP", "VBN", "RP", "CC", "VBD", "TO", "VB", "NNP", "NNP", "NN", "VBD", "VBG", ":", "CC", "PRP", "VBD", "RB", "VBG", "IN", "DT", "NNS", ":", ":", "PRP", "VBD", "VBG", "IN", "NN", "NNP", "NNP", "DT", "NN", "VBD", ",", "DT", "PRP", "VBD", "VBD", "DT", "JJ", "NN", "POS", "NNP", "NNP", "DT", "NN", "RB", "IN", "JJ", "."], "aSentId": 2, "answer": "Ahh!!! Assholes.", "movie_name": "Feast.dial", "answer_ne_tagged": {}, "question_ne_tagged": {"DATE": ["winter"]}}, {"speaker1": "CHIEF", "speaker2": "COLLEGE BOY", "docId": 64, "answer_pos_tagged": ["RB", "VBD", "JJ", ",", "VBZ", "."], "qSentId": 3, "question": "Hey, relax, I nearly shit myself when my boss pulled that one on me. What was that?", "question_pos_tagged": ["PRP", ",", "NN", ",", "PRP", "RB", "NN", "PRP", "WRB", "PRP$", "NN", "VBD", "IN", "CD", "IN", "NNP", "NNP", "VBD", "IN", "."], "aSentId": 3, "answer": "Once was plenty, fellas.", "movie_name": "Feast.dial", "answer_ne_tagged": {}, "question_ne_tagged": {}}, {"speaker1": "CHIEF", "speaker2": "MEAN GREEN", "docId": 64, "answer_pos_tagged": ["NNP", "PRP", "VBD", "RB", ".", "PRP", "MD", "RB", "VB", "NNP", "NNP", "CD", "JJR", "NN", "."], "qSentId": 5, "question": "Shhhh...", "question_pos_tagged": ["NNP", ":"], "aSentId": 5, "answer": "Stop it right there! You will not rape Mother Nature one more day!", "movie_name": "Feast.dial", "answer_ne_tagged": {}, "question_ne_tagged": {}}, {"speaker1": "CHIEF", "speaker2": "MEAN GREEN", "docId": 64, "answer_pos_tagged": ["CC", "PRP", "VBP", "DT", "NN", "IN", "DT", "NNP", "TO", "VB", "DT", "NN", "IN", "DT", "NNS", ".", "DT", "VBZ", "NN", "NN", ".", "DT", "NNS", "IN", "DT", "NNS", "VBG", "VBG", "NN", "TO", "PRP$", "NNS", ",", "CC", "PRP$", "NN", "VBZ", "NN", "IN", "PRP$", "NNS", "WDT", "NN", "DT", "NN", "NN", ".", "CC", "PRP", "MD", "RB", "VB", "VBN", "IN", "NN", "IN", "DT", "NN", ".", "RB", "RB", ".", "RB", "RB", "."], "qSentId": 6, "question": "Whoa! Whoa! Whoa! Take it easy! We have a permit!", "question_pos_tagged": ["NNP", ":", "NNP", ".", "NNP", ".", "NNP", "PRP", "JJ", ".", "PRP", "VBP", "DT", "NN", "."], "aSentId": 6, "answer": "And we have an injunction from the State to prevent any dumping in these caverns! This is virgin land! The aqueducts in these caves bring drinking water to our families, and its piping provides drainage for our farms that enrich this barren land! And it won't be tainted by waste of any kind! Not now! Not ever!", "movie_name": "Feast.dial", "answer_ne_tagged": {"ORGANIZATION": ["State"]}, "question_ne_tagged": {}}, {"speaker1": "CHIEF", "speaker2": "MEAN GREEN", "docId": 64, "answer_pos_tagged": ["PRP", "MD", "VB", "NN", "IN", "NN", ".", "NNP", "NNP", "PRP", ".", "NNP", "CD", "IN", "DT", "JJ", "NN", ".", ".", ".", "PRP", "VBD", "PRP", "NN", ",", "NN", "''", "NNP", "NNP", ",", "WRB", "VBP", "PRP", "RB", "VBG", "IN", "DT", "NNS", ".", "NNP", "PRP", "DT", "NNS", ".", ".", "."], "qSentId": 7, "question": "Fine, just back off! Let's roll... Now-now-now! How do you guys always know where we're going?", "question_pos_tagged": ["NN", ",", "RB", "RB", "IN", ".", "NNP", "POS", "NN", ":", "JJ", ".", "WRB", "VBP", "PRP", "VBZ", "RB", "VB", "WRB", "PRP", "VBP", "VBG", "."], "aSentId": 7, "answer": "I'll tell ya next time! NOW MOVE IT! Score one for the green team!!! We saved you today, ol' gal. Sister, why do you always swing for the fences? Give me the keys!!!", "movie_name": "Feast.dial", "answer_ne_tagged": {}, "question_ne_tagged": {}}, {"speaker1": "BEER GUY", "speaker2": "COACH", "docId": 64, "answer_pos_tagged": ["IN", "WP", ",", "MD", "PRP", "VB", "."], "qSentId": 8, "question": "I mean, we'd been together for so long and then... bang! She drops me. Since then, it's been like a damn country song", "question_pos_tagged": ["PRP", "VBP", ",", "PRP", "MD", "VB", "RB", "IN", "RB", "RB", "CC", "RB", ":", "NN", ".", "PRP", "VBZ", "NNP", "NNP", "RB", ",", "PRP", "VBZ", "VBN", "IN", "DT", "NN", "NN", "IN"], "aSentId": 8, "answer": "For what, may I ask?", "movie_name": "Feast.dial", "answer_ne_tagged": {}, "question_ne_tagged": {}}, {"speaker1": "BEER GUY", "speaker2": "COACH", "docId": 64, "answer_pos_tagged": ["PRP", "VBP", ",", "NNP", ",", "VBG", "PRP", "IN", "DT", "JJ", "NN", "VBZ", "NN", "NN", "."], "qSentId": 9, "question": "JC Penny. Spring wear.", "question_pos_tagged": ["NNP", "NNP", "NNP", "NN", "."], "aSentId": 9, "answer": "You know, Chach, catching you at this low point is pure serendipity.", "movie_name": "Feast.dial", "answer_ne_tagged": {"PERSON": ["Chach"]}, "question_ne_tagged": {}}, {"speaker1": "BEER GUY", "speaker2": "COACH", "docId": 64, "answer_pos_tagged": ["IN", "PRP", "VBP", "DT", "JJ", "IN", "NN", "CC", "VB", "NNP", "NNP", "PRP$", "NN", "RB", "VBZ", "DT", "NN", "TO", "DT", "JJ", "NNP", "NNP", "PRP", "DT", "NN", ",", "IN", "PRP", "MD", "VB", "TO", "VB", "PRP", "DT", "NN", "CC", "NN", "PRP$", "NN", "NNP", "PRP", "VBP", "DT", "NN", ":"], "qSentId": 10, "question": "Why is that?", "question_pos_tagged": ["WRB", "VBZ", "IN", "."], "aSentId": 10, "answer": "Because I take the rubble of man and build superstars. In my briefcase here is a doorway to a self-help sensation. Give me a minute, because I'd like to buy you a drink and change your life forever. I have a brochure --", "movie_name": "Feast.dial", "answer_ne_tagged": {}, "question_ne_tagged": {}}, {"speaker1": "EDGY CAT", "speaker2": "BOZO", "docId": 64, "answer_pos_tagged": ["NNP", ",", "RB", "IN", "POS", "DT", "JJ", "CD", "."], "qSentId": 11, "question": "That's all she wrote... What?!", "question_pos_tagged": ["DT", "VBZ", "DT", "PRP", "VBD", ":", "WP", ".", "."], "aSentId": 11, "answer": "Ohhh, now that's a rough one.", "movie_name": "Feast.dial", "answer_ne_tagged": {}, "question_ne_tagged": {}}, {"speaker1": "EDGY CAT", "speaker2": "BOZO", "docId": 64, "answer_pos_tagged": ["NNP", "NN", "MD", "VB", "JJ", "NNP", "NNP", "RB", "."], "qSentId": 12, "question": "That's motherfuckin' impossible!", "question_pos_tagged": ["DT", "VBZ", "NN", "''", "JJ", "."], "aSentId": 12, "answer": "Yoh anga will be yoh downfah. Go again?", "movie_name": "Feast.dial", "answer_ne_tagged": {}, "question_ne_tagged": {}}, {"speaker1": "EDGY CAT", "speaker2": "BOZO", "docId": 64, "answer_pos_tagged": ["UH", ",", "VBP", "NNP", "NNP", "NNP", "."], "qSentId": 13, "question": "Goddamn it! NO!", "question_pos_tagged": ["NNP", "PRP", ".", "DT", "."], "aSentId": 13, "answer": "Oh, come on. Crape Diem!", "movie_name": "Feast.dial", "answer_ne_tagged": {}, "question_ne_tagged": {}}, {"speaker1": "HERO", "speaker2": "BARTENDER", "docId": 64, "answer_pos_tagged": ["PRP", "VBD", "PRP", "RB", "RB", ",", "NN", "."], "qSentId": 14, "question": "Unless you people want to die you'll do what I say and you'll do it fast!", "question_pos_tagged": ["IN", "PRP", "NNS", "VBP", "TO", "VB", "PRP", "MD", "VB", "WP", "PRP", "VBP", "CC", "PRP", "MD", "VB", "PRP", "VB", "."], "aSentId": 14, "answer": "You hold it right there, mister.", "movie_name": "Feast.dial", "answer_ne_tagged": {}, "question_ne_tagged": {}}, {"speaker1": "HERO", "speaker2": "BARTENDER", "docId": 64, "answer_pos_tagged": ["NNP", "DT", "NN", "."], "qSentId": 15, "question": "A storm of hell's coming down on this place any minute!", "question_pos_tagged": ["DT", "NN", "IN", "NN", "POS", "VBG", "IN", "IN", "DT", "NN", "DT", "NN", "."], "aSentId": 15, "answer": "Drop the canon!", "movie_name": "Feast.dial", "answer_ne_tagged": {}, "question_ne_tagged": {}}, {"speaker1": "HERO", "speaker2": "BARTENDER", "docId": 64, "answer_pos_tagged": ["PRP", "MD", "VB", "PRP", "CC", "RB", "RB", "VBP", "IN", "PRP", "."], "qSentId": 16, "question": "I'm not armed now, just hear me out.", "question_pos_tagged": ["PRP", "VBP", "RB", "VBN", "RB", ",", "RB", "JJ", "PRP", "IN", "."], "aSentId": 16, "answer": "I'll drop you and not even think about it!", "movie_name": "Feast.dial", "answer_ne_tagged": {}, "question_ne_tagged": {}}, {"speaker1": "HERO", "speaker2": "BARTENDER", "docId": 64, "answer_pos_tagged": ["PRP", "VBD", "CD", "JJ", "TO", ":"], "qSentId": 17, "question": "Let me explain!", "question_pos_tagged": ["NNP", "PRP", "VB", "."], "aSentId": 17, "answer": "You got one second to --", "movie_name": "Feast.dial", "answer_ne_tagged": {}, "question_ne_tagged": {}}, {"speaker1": "HERO", "speaker2": "BARTENDER", "docId": 64, "answer_pos_tagged": ["WP", "VBP", "PRP", "."], "qSentId": 18, "question": "Take a good look and listen to me! There's at least a four of these things out there! I saw one of them tear up five men like they were corn on the cob! I don't know what they are. I don't know where they came from. All I do know is that these fuckers are fast, nasty, and hungry. And they can fly. Not to mention they got claws like Ginsu knifes and more teeth than a chainsaw. They're like goddamn blood hungry biker tattoos come to life. They're clocking us. Right now. And we have to lock this bar down! That means doors, windows, drains, and basements. We have to do it fast! You! Get on that phone. Call the cops, National Guard, townies, whoever kicks ass and get 'em out here. Any questions?", "question_pos_tagged": ["NNP", "DT", "JJ", "NN", "CC", "RB", "TO", "PRP", ".", "EX", "VBZ", "IN", "JJS", "DT", "CD", "IN", "DT", "NNS", "IN", "RB", ".", "PRP", "VBD", "CD", "IN", "PRP", "JJ", "RP", "CD", "NNS", "IN", "PRP", "VBD", "NN", "IN", "DT", "NN", ".", "PRP", "VBP", "RB", "VB", "WP", "PRP", "NNP", "PRP", "VBP", "RB", "VB", "WRB", "PRP", "VBD", "NNP", "NNP", "NNP", "VBP", "RB", "VBZ", "IN", "DT", "NNS", "VBP", "RB", ",", "NN", ",", "CC", "NNP", "CC", "PRP", "MD", "NNP", "NNP", "TO", "VB", "PRP", "VBD", "NNS", "IN", "NNP", "NNS", "CC", "JJR", "NN", "IN", "DT", "NNP", "NNP", "VBP", "IN", "NN", "NN", "NN", "NN", "NNS", "VBP", "TO", "NNP", "NNP", "VBP", "VBG", "NNP", "NNP", "NNP", "CC", "PRP", "VBP", "TO", "VB", "DT", "NN", "IN", ".", "DT", "VBZ", "NNS", ",", "VBZ", ",", "VBZ", ",", "CC", "NNP", "NNP", "VBP", "TO", "VB", "PRP", "VB", ".", "PRP", ".", "NNP", "IN", "DT", "NNP", "NNP", "DT", "NNS", ",", "NNP", "NNP", ",", "VBZ", ",", "RB", "VBZ", "NN", "CC", "VB", "JJ", "IN", "NNP", "NNP", "NNS", "."], "aSentId": 18, "answer": "Who are you?", "movie_name": "Feast.dial", "answer_ne_tagged": {}, "question_ne_tagged": {"ORGANIZATION": ["National Guard"]}}, {"speaker1": "BOSS MAN", "speaker2": "BARTENDER", "docId": 64, "answer_pos_tagged": ["NNP", "."], "qSentId": 20, "question": "Is it clear?!", "question_pos_tagged": ["VBZ", "PRP", "RB", ".", "."], "aSentId": 20, "answer": "Yeah.", "movie_name": "Feast.dial", "answer_ne_tagged": {}, "question_ne_tagged": {}}, {"speaker1": "BOSS MAN", "speaker2": "BARTENDER", "docId": 64, "answer_pos_tagged": ["NNP", ",", "PRP", "VBD", "DT", "NN", "."], "qSentId": 21, "question": "Is there a gun pointing at you?", "question_pos_tagged": ["VBZ", "EX", "DT", "NN", "VBG", "IN", "PRP", "."], "aSentId": 21, "answer": "Nah, I got the gun.", "movie_name": "Feast.dial", "answer_ne_tagged": {}, "question_ne_tagged": {}}, {"speaker1": "BOSS MAN", "speaker2": "BARTENDER", "docId": 64, "answer_pos_tagged": ["PRP$", "NN", "."], "qSentId": 22, "question": "Alright goddamn it! Who shot me!? Who did it!? My goddamn foot is gone! Who fuckin' shot me? Who fuckin' shot me!?", "question_pos_tagged": ["NNP", "VBD", "PRP", ".", "WP", "RB", "PRP", ".", ".", "WP", "VBD", "PRP", ".", ".", "NNP", "NN", "NN", "VBZ", "VBN", ".", "WP", "NN", "''", "NN", "PRP", ".", "WP", "NN", "''", "NN", "PRP", ".", "."], "aSentId": 22, "answer": "Her fella.", "movie_name": "Feast.dial", "answer_ne_tagged": {}, "question_ne_tagged": {}}, {"speaker1": "BOSS MAN", "speaker2": "HEROINE", "docId": 64, "answer_pos_tagged": ["NNP", "NNP", "NNP", "VBD", "IN", "NN", "DT", "NNS", "NN", "IN", "PRP", "VBP", "RB", "VBN", "NNP", "NNP", "NN", "IN", "NNP", "NNP", "NN", ",", "JJ", ",", "NNP", "NNP", "VBD", "IN", "CD", "IN", "PRP$", "NNS", "IN", "NN", "."], "qSentId": 23, "question": "Jesus Christ on the cross... someone make sense.", "question_pos_tagged": ["NNP", "NNP", "IN", "DT", "NN", ":", "NN", "VBP", "NN", "."], "aSentId": 23, "answer": "Easy. We're surrounded by something the likes none of you have ever seen before. Some kind of animals. Real fast, volatile, predators. One went through three of your patrons like nothing.", "movie_name": "Feast.dial", "answer_ne_tagged": {}, "question_ne_tagged": {}}, {"speaker1": "BOSS MAN", "speaker2": "HEROINE", "docId": 64, "answer_pos_tagged": ["PRP", "RB", "VBD", "PRP", "RB", "."], "qSentId": 24, "question": "So, your dead hubby shot me twice, three of my customers have been eaten, and there are angry creatures outside?", "question_pos_tagged": ["IN", ",", "PRP$", "NN", "NN", "NN", "PRP", "NN", ",", "CD", "IN", "PRP$", "NNS", "VBP", "VBN", "VBN", ",", "CC", "EX", "VBP", "JJ", "NNS", "IN", "."], "aSentId": 24, "answer": "He only shot you once.", "movie_name": "Feast.dial", "answer_ne_tagged": {}, "question_ne_tagged": {}}, {"speaker1": "BOSS MAN", "speaker2": "HEROINE", "docId": 64, "answer_pos_tagged": ["PRP", "VBD", "PRP", "DT", "JJ", "NN", "."], "qSentId": 25, "question": "Huh?", "question_pos_tagged": ["NNP", "."], "aSentId": 25, "answer": "He shot you the other time.", "movie_name": "Feast.dial", "answer_ne_tagged": {}, "question_ne_tagged": {}}, {"speaker1": "HEROINE", "speaker2": "TUFFY", "docId": 64, "answer_pos_tagged": ["UH", "PRP$", "NN", ".", "NNP", "NN", ".", "NNP", "NNP", "."], "qSentId": 26, "question": "That's not it. Four are here, but there's three others... which I can't account for. We need to lock this place down. Is everyone in this room?", "question_pos_tagged": ["DT", "VBZ", "RB", "NNP", "NNP", "VBP", "RB", ",", "CC", "EX", "VBZ", "CD", "NNS", ":", "WDT", "PRP", "MD", "RB", "VB", "NNP", "NNP", "VBP", "TO", "VB", "DT", "NN", "NNP", "NNP", "NN", "IN", "DT", "NN", "."], "aSentId": 26, "answer": "Oh my god! My son! My SON!", "movie_name": "Feast.dial", "answer_ne_tagged": {}, "question_ne_tagged": {}}, {"speaker1": "HEROINE", "speaker2": "TUFFY", "docId": 64, "answer_pos_tagged": ["NNP", ":", "NNP", "POS", "VBG", ".", "NNP", "POS", "VBG", "."], "qSentId": 27, "question": "Wait!", "question_pos_tagged": ["NN", "``"], "aSentId": 27, "answer": "Cody! Mommy's coming! Mommy's coming!", "movie_name": "Feast.dial", "answer_ne_tagged": {}, "question_ne_tagged": {}}, {"speaker1": "PARA", "speaker2": "BELLE", "docId": 64, "answer_pos_tagged": ["WP", "VBZ", "DT", ".", "DT", "NN", "NN", "CC", "NN", "."], "qSentId": 29, "question": "Thank you, but I don't need any help --", "question_pos_tagged": ["NNP", "PRP", ",", "CC", "PRP", "VBP", "RB", "VB", "DT", "NN", ":"], "aSentId": 29, "answer": "What's this? A power magnet or something?", "movie_name": "Feast.dial", "answer_ne_tagged": {}, "question_ne_tagged": {}}, {"speaker1": "PARA", "speaker2": "BELLE", "docId": 64, "answer_pos_tagged": ["PRP", "VBD", "RB", "VB", "PRP", "IN", "DT", "NN", "NN", "."], "qSentId": 30, "question": "No. It's nothing.", "question_pos_tagged": ["NN", "PRP", "VBZ", "NN", "."], "aSentId": 30, "answer": "I didn't peg you for a con man.", "movie_name": "Feast.dial", "answer_ne_tagged": {}, "question_ne_tagged": {}}, {"speaker1": "PARA", "speaker2": "BELLE", "docId": 64, "answer_pos_tagged": ["NNS", "IN", "NN", "IN", "RB", "VBZ", "."], "qSentId": 31, "question": "Hey, it pays more than the couch.", "question_pos_tagged": ["PRP", ",", "PRP", "VBZ", "JJR", "IN", "DT", "JJ", "."], "aSentId": 31, "answer": "Lots of stuff around here does.", "movie_name": "Feast.dial", "answer_ne_tagged": {}, "question_ne_tagged": {}}, {"speaker1": "ADULTERER", "speaker2": "HEROINE", "docId": 64, "answer_pos_tagged": ["PRP", "MD", "RB", "VB", "DT", "."], "qSentId": 32, "question": "I have a signal! I have -- Diane? Diane listen to me... get the kids and get in the basement... do it right now... I'll explain later. Not now! I'm at a bar... look... shut up! JUST SHUT UP AND GET IN THE FUCKING BASEMENT, DIANE! Diane! Diane?... Hello? Damn it! I lost the signal! Okay. Okay. Look now, I gotta get outta here! I gotta go! My wife... See my wife is alone... She could be in trouble. I GOTTA GO!", "question_pos_tagged": ["PRP", "VBP", "DT", "NN", ".", "PRP", "VBP", ":", "NNP", ".", "NNP", "RB", "TO", "PRP", ":", "VB", "DT", "NNS", "CC", "VB", "IN", "DT", "NN", ":", "VBP", "PRP", "RB", "RB", ":", "PRP", "MD", "VB", "NNP", "NNP", "RB", ".", "PRP", "VBP", "IN", "DT", "NN", ":", "NN", ":", "NN", "IN", ".", "NNP", "NNP", "NNP", "NNP", "NNP", "NNP", "NNP", "NNP", "NNP", ",", "NNP", ".", "NNP", ".", "NNP", ".", ":", "NNP", ".", "NNP", "PRP", ".", "PRP", "VBD", "DT", "NN", ".", "NNP", "NNP", "NNP", "RB", ",", "PRP", "VBD", "NN", "NN", "NN", "RB", ".", "PRP", "VBD", "NN", "NN", ".", "NNP", "NN", ":", "NNP", "PRP$", "NN", "VBZ", "RB", ":", "PRP", "MD", "VB", "IN", "NNP", "NNP", "NNP", "NNP", "NNP", "."], "aSentId": 32, "answer": "I wouldn't do that.", "movie_name": "Feast.dial", "answer_ne_tagged": {}, "question_ne_tagged": {"PERSON": ["Diane"]}}, {"speaker1": "ADULTERER", "speaker2": "HEROINE", "docId": 64, "answer_pos_tagged": ["PRP", "MD", "VB", "PRP$", "NN", ",", "CC", "RB", "JJ", ".", "NNP", "NN", "POS", "DT", "RBR", "IN", "NN", "NNS", "IN", "RB", "VBG", "IN", "NNP", "NNP", "VBP", "RB", "IN", "JJ", "NN", "TO", "VB", "DT", "NN", "IN", "PRP", "NNP", "CC", "PRP", "RB", "VBP", "IN", "IN", "PRP", "VBP", "RB", ",", "RB", "PRP", "VBP", "RB", "RB", "NNP", "NNP", "VBP", "PRP", "."], "qSentId": 33, "question": "Fuck you, bitch!", "question_pos_tagged": ["NNP", "PRP", ",", "VBP", "."], "aSentId": 33, "answer": "You can risk your life, but not mine! My daughter's no more than twenty miles from here waiting for me. I have just as much reason to leave this place as you do. But I also know that if they're here, then they're not there yet. You understand me?", "movie_name": "Feast.dial", "answer_ne_tagged": {}, "question_ne_tagged": {}}, {"speaker1": "ADULTERER", "speaker2": "HEROINE", "docId": 64, "answer_pos_tagged": ["PRP", "VBP", "PRP", ".", "."], "qSentId": 34, "question": "Get the fuck off...", "question_pos_tagged": ["NN", "DT", "NN", "RP", ":"], "aSentId": 34, "answer": "You understand me!?", "movie_name": "Feast.dial", "answer_ne_tagged": {}, "question_ne_tagged": {}}, {"speaker1": "ADULTERER", "speaker2": "HEROINE", "docId": 64, "answer_pos_tagged": ["RB", "VBP", "IN", "JJ", "NN", "NN", "RB", "CC", "PRP", "MD", "VB", "PRP", "IN", "NN", "TO", "NNS", "."], "qSentId": 35, "question": "Yes!", "question_pos_tagged": ["NNS", "VBP"], "aSentId": 35, "answer": "Now pull that tough boy shit again and I'll slice you from neck to nuts!", "movie_name": "Feast.dial", "answer_ne_tagged": {}, "question_ne_tagged": {}}, {"speaker1": "ADULTERER", "speaker2": "HEROINE", "docId": 64, "answer_pos_tagged": ["PRP", "MD", "RB", "VB", "VBG", "PRP", "IN", "."], "qSentId": 36, "question": "You can't keep me here. This is bullshit. Fuckin' bullshit. This is fucking BULLSHIT!", "question_pos_tagged": ["PRP", "MD", "RB", "VB", "PRP", "NNP", "NNP", "VBZ", "NNP", "NNP", "POS", "NNP", "NNP", "VBZ", "VBG", "NN", "."], "aSentId": 36, "answer": "We can't risk letting them in.", "movie_name": "Feast.dial", "answer_ne_tagged": {}, "question_ne_tagged": {}}, {"speaker1": "NEWSCASTER", "speaker2": "HEROINE", "docId": 64, "answer_pos_tagged": ["PRP$", "NN", "POS", "IN", "NNP", "NNP", "."], "qSentId": 38, "question": "And now, we head to our man on the scene with a live look at tomorrow's event in Red Mountain.", "question_pos_tagged": ["CC", "RB", ",", "PRP", "VBP", "TO", "PRP$", "NN", "IN", "DT", "NN", "IN", "DT", "JJ", "NN", "IN", "NN", "POS", "NN", "IN", "NNP", "NNP", "."], "aSentId": 38, "answer": "My daughter's in Red Mountain.", "movie_name": "Feast.dial", "answer_ne_tagged": {"LOCATION": ["Red Mountain"]}, "question_ne_tagged": {"LOCATION": ["Red Mountain"]}}, {"speaker1": "NEWSCASTER", "speaker2": "HEROINE", "docId": 64, "answer_pos_tagged": ["UH", "DT", "."], "qSentId": 39, "question": "Can you hear us? Apparently we're having some technical difficulties...", "question_pos_tagged": ["NNP", "PRP", "VB", "PRP", ".", "RB", "PRP", "VBP", "VBG", "DT", "JJ", "NNS", ":"], "aSentId": 39, "answer": "Oh no.", "movie_name": "Feast.dial", "answer_ne_tagged": {}, "question_ne_tagged": {}}, {"speaker1": "HEROINE", "speaker2": "HERO", "docId": 64, "answer_pos_tagged": ["WP", "VBZ", "VBN", "''", "IN", ".", "DT", "NNS", "VBP", "RP", "."], "qSentId": 41, "question": "We barricaded ourselves in the cellar. Then it was just listening. We heard those things destroy an entire heard of livestock. They just kept coming. Closer and closer, consuming anything in the way. Slashing, feeding and licking the bones clean. Just when we said our prayers, the first ray of sun hit the house... That first beam of sunlight drove 'em away. Somewhere. We called who we could and then decided to run for it. We didn't see a soul the whole drive out. When the tank went dry, we came upon a gas station to refill.", "question_pos_tagged": ["PRP", "VBD", "NNS", "IN", "DT", "NNP", "NNP", "PRP", "VBD", "RB", "NNP", "NNP", "NN", "DT", "NNS", "VBP", "DT", "JJ", "NN", "IN", "NNP", "NNP", "RB", "VBD", "NNP", "NNP", "CC", "JJR", ",", "VBG", "NN", "IN", "DT", "NNP", "NNP", ",", "VBG", "CC", "VBG", "DT", "NNS", "NNP", "NNP", "WRB", "PRP", "VBD", "PRP$", "NNS", ",", "DT", "JJ", "NN", "IN", "NN", "VBD", "DT", "NN", ":", "DT", "JJ", "NN", "IN", "NN", "VBD", "JJ", "NNP", "NNP", "NNP", "VBD", "WP", "PRP", "MD", "CC", "RB", "VBD", "TO", "VB", "IN", "NNP", "NNP", "VBD", "RB", "VB", "DT", "NN", "DT", "JJ", "JJ", "NNP", "NNP", "DT", "NN", "VBD", "JJ", ",", "PRP", "VBD", "IN", "DT", "NN", "NN", "TO", "VB", "."], "aSentId": 41, "answer": "What's goin' on? The pumps are off.", "movie_name": "Feast.dial", "answer_ne_tagged": {}, "question_ne_tagged": {}}, {"speaker1": "HEROINE", "speaker2": "HERO", "docId": 64, "answer_pos_tagged": ["NNP", "IN", "DT", "NN", "."], "qSentId": 42, "question": "They've been here!", "question_pos_tagged": ["PRP", "VBP", "VBN", "RB", "."], "aSentId": 42, "answer": "Turn on the pump!", "movie_name": "Feast.dial", "answer_ne_tagged": {}, "question_ne_tagged": {}}, {"speaker1": "HEROINE", "speaker2": "HERO", "docId": 64, "answer_pos_tagged": ["NNP", "PRP", "IN", "PRP", "VBP", "NNP", "NNP", "PRP", "IN", "."], "qSentId": 43, "question": "We had no time. All we knew was the sun was dropping and we had to get enough fuel to make it through the night at 90 miles per hour...", "question_pos_tagged": ["PRP", "VBD", "DT", "NNP", "NNP", "PRP", "VBD", "VBD", "DT", "NN", "VBD", "VBG", "CC", "PRP", "VBD", "TO", "VB", "RB", "NN", "TO", "VB", "PRP", "IN", "DT", "NN", "IN", "CD", "NNS", "IN", "PRP$", ":"], "aSentId": 43, "answer": "Suck it down you metal bitch. Suck it down.", "movie_name": "Feast.dial", "answer_ne_tagged": {}, "question_ne_tagged": {"TIME": ["night"]}}, {"speaker1": "HEROINE", "speaker2": "HERO", "docId": 64, "answer_pos_tagged": ["NNP", "PRP", ".", "NNP", "IN", "DT", "NN", ",", "NN", "."], "qSentId": 44, "question": "It happened fast...", "question_pos_tagged": ["PRP", "VBD", "RB", ":"], "aSentId": 44, "answer": "Move it! Get in the car, baby.", "movie_name": "Feast.dial", "answer_ne_tagged": {}, "question_ne_tagged": {}}, {"speaker1": "HEROINE", "speaker2": "HERO", "docId": 64, "answer_pos_tagged": ["NNP", ":"], "qSentId": 45, "question": "That's when I saw three others... just for a second.", "question_pos_tagged": ["DT", "VBZ", "WRB", "PRP", "VBP", "CD", "NNS", ":", "RB", "IN", "DT", "JJ", "."], "aSentId": 45, "answer": "Roll!", "movie_name": "Feast.dial", "answer_ne_tagged": {}, "question_ne_tagged": {}}, {"speaker1": "HEROINE", "speaker2": "HERO", "docId": 64, "answer_pos_tagged": ["NN", "``", "PRP", "VBD", "PRP", "."], "qSentId": 46, "question": "Close the roof!", "question_pos_tagged": ["JJ", "DT", "NN", "."], "aSentId": 46, "answer": "Shit! We made it!", "movie_name": "Feast.dial", "answer_ne_tagged": {}, "question_ne_tagged": {}}, {"speaker1": "HEROINE", "speaker2": "BARTENDER", "docId": 64, "answer_pos_tagged": ["CC", "DT", "NN", "."], "qSentId": 47, "question": "And that's how I ended up here.", "question_pos_tagged": ["CC", "DT", "VBZ", "WRB", "PRP", "VBD", "RP", "RB", "."], "aSentId": 47, "answer": "And the head?", "movie_name": "Feast.dial", "answer_ne_tagged": {}, "question_ne_tagged": {}}, {"speaker1": "HEROINE", "speaker2": "BARTENDER", "docId": 64, "answer_pos_tagged": ["IN", ",", "PRP$", "NN", "VBD", "PRP", "."], "qSentId": 48, "question": "I don't want to talk about that.", "question_pos_tagged": ["PRP", "VBP", "RB", "VB", "TO", "VB", "IN", "DT", "."], "aSentId": 48, "answer": "So, your husband ditched you?", "movie_name": "Feast.dial", "answer_ne_tagged": {}, "question_ne_tagged": {}}, {"speaker1": "HEROINE", "speaker2": "BARTENDER", "docId": 64, "answer_pos_tagged": ["NNP", ",", "NN", "VBZ", "JJ", "."], "qSentId": 49, "question": "No. It was wild out there. No time to think. We just moved. He didn't leave me. He just ran.", "question_pos_tagged": ["NN", "PRP", "VBD", "VBN", "RP", "NNP", "NNP", "NN", "TO", "NNP", "NNP", "RB", "NNP", "NNP", "VBD", "RB", "VB", "NNP", "NNP", "RB", "VBD", "."], "aSentId": 49, "answer": "Well, justice is funny.", "movie_name": "Feast.dial", "answer_ne_tagged": {}, "question_ne_tagged": {}}, {"speaker1": "BOZO", "speaker2": "GRANDPA", "docId": 64, "answer_pos_tagged": ["NNP", "."], "qSentId": 50, "question": "You!", "question_pos_tagged": ["PRP", "VBP"], "aSentId": 50, "answer": "Wha?", "movie_name": "Feast.dial", "answer_ne_tagged": {}, "question_ne_tagged": {}}, {"speaker1": "BOZO", "speaker2": "GRANDPA", "docId": 64, "answer_pos_tagged": ["PRP", "VBP", "RB", "VB", "DT", "NN", "."], "qSentId": 51, "question": "You gotta know somethin', you're old.", "question_pos_tagged": ["PRP", "VBD", "NNS", "VBP", "IN", "POS", ",", "PRP", "VBP", "JJ", "."], "aSentId": 51, "answer": "I don't know a thing.", "movie_name": "Feast.dial", "answer_ne_tagged": {}, "question_ne_tagged": {}}, {"speaker1": "BOZO", "speaker2": "GRANDPA", "docId": 64, "answer_pos_tagged": ["DT", "NN"], "qSentId": 52, "question": "Old people know stuff like this. Legends, tall tales, shit like that.", "question_pos_tagged": ["NNP", "NNS", "VBP", "NN", "IN", "NNP", "NNPS", ",", "JJ", "NNS", ",", "NN", "IN", "DT", "."], "aSentId": 52, "answer": "No!", "movie_name": "Feast.dial", "answer_ne_tagged": {}, "question_ne_tagged": {}}, {"speaker1": "BOZO", "speaker2": "GRANDPA", "docId": 64, "answer_pos_tagged": ["PRP", "VBP", "RB", "VB", "NN", "."], "qSentId": 53, "question": "Spill it!", "question_pos_tagged": ["NNP", "PRP", "."], "aSentId": 53, "answer": "I don't know anything!", "movie_name": "Feast.dial", "answer_ne_tagged": {}, "question_ne_tagged": {}}, {"speaker1": "ROADIE", "speaker2": "PARA", "docId": 64, "answer_pos_tagged": ["NNP", ",", "PRP", "VBZ", "DT", "NN", ",", "CC", "PRP", "VBZ", "PRP$", "NNP", "NNP", "NNP", "."], "qSentId": 55, "question": "You're a clever man. Why do you take shit from him?", "question_pos_tagged": ["PRP", "VBP", "DT", "NN", "NNP", "NNP", "VBP", "PRP", "VB", "NN", "IN", "PRP", "."], "aSentId": 55, "answer": "Yeah, he's an ass, but he's my brother. Que sera-sera.", "movie_name": "Feast.dial", "answer_ne_tagged": {}, "question_ne_tagged": {}}, {"speaker1": "ROADIE", "speaker2": "PARA", "docId": 64, "answer_pos_tagged": ["NNP", "."], "qSentId": 56, "question": "Your brother, huh?", "question_pos_tagged": ["PRP$", "NN", ",", "NN", "."], "aSentId": 56, "answer": "Yep.", "movie_name": "Feast.dial", "answer_ne_tagged": {}, "question_ne_tagged": {}}, {"speaker1": "ROADIE", "speaker2": "PARA", "docId": 64, "answer_pos_tagged": ["NNP", "NN", ",", "PRP", "VBP", "NNP", "NNP", "VBZ", "JJR", "NNS", "."], "qSentId": 57, "question": "Same parents?", "question_pos_tagged": ["NNP", "NNS", "."], "aSentId": 57, "answer": "Look man, I read books. He reads bumper stickers.", "movie_name": "Feast.dial", "answer_ne_tagged": {}, "question_ne_tagged": {}}, {"speaker1": "GRANDPA", "speaker2": "BOZO", "docId": 64, "answer_pos_tagged": ["UH", ",", "RB", "PRP", "VBP", "NN", "TO", "VB", "."], "qSentId": 58, "question": "You're gonna need a whole lot more than that to get outta here alive.", "question_pos_tagged": ["PRP", "VBP", "JJ", "NN", "NN", "DT", "JJ", "NN", "RBR", "IN", "DT", "TO", "VB", "NN", "RB", "JJ", "."], "aSentId": 58, "answer": "Oh, now you have something to say?", "movie_name": "Feast.dial", "answer_ne_tagged": {}, "question_ne_tagged": {}}, {"speaker1": "GRANDPA", "speaker2": "BOZO", "docId": 64, "answer_pos_tagged": ["UH", ".", "CC", "WP", "VBZ", "IN", "."], "qSentId": 59, "question": "You young'uns worry about weapons, I'm thinkin' 'bout strategy.", "question_pos_tagged": ["PRP", "VBZ", "JJ", "IN", "NNS", ",", "PRP", "VBP", "JJ", "''", "IN", "NN", "."], "aSentId": 59, "answer": "Oh? And what's that?", "movie_name": "Feast.dial", "answer_ne_tagged": {}, "question_ne_tagged": {}}, {"speaker1": "GRANDPA", "speaker2": "BOZO", "docId": 64, "answer_pos_tagged": ["DT", "VBZ", "IN", "NNS", "CC", "NNS", ",", "JJ", "NN", "."], "qSentId": 60, "question": "Sit still, look less like a meal.", "question_pos_tagged": ["NN", "RB", ",", "VBP", "JJR", "IN", "DT", "NN", "."], "aSentId": 60, "answer": "That's for bears and sharks, chunky chew.", "movie_name": "Feast.dial", "answer_ne_tagged": {}, "question_ne_tagged": {}}, {"speaker1": "BOZO", "speaker2": "HEROINE", "docId": 64, "answer_pos_tagged": ["NN", "PRP", "VBP", "VBN", "IN", "."], "qSentId": 61, "question": "What are you gonna do? Throw your teeth at 'em? Sit down, Cocoon. You! Zorba! You're coming too! Now gimme the keys.", "question_pos_tagged": ["WP", "VBP", "PRP", "VBP", "NNS", "VBP", ".", "NNP", "PRP$", "NN", "IN", "JJ", ".", "NNP", "RB", ",", "NNP", "NNP", ".", "NNP", ".", "PRP", "VBP", "VBG", "RB", ".", "RB", "VBP", "PRP", "DT", "NNS", "."], "aSentId": 61, "answer": "No. You're locked in.", "movie_name": "Feast.dial", "answer_ne_tagged": {}, "question_ne_tagged": {}}, {"speaker1": "BOZO", "speaker2": "HEROINE", "docId": 64, "answer_pos_tagged": ["DT", "CD", "MD", "VB", "IN", "DT", "JJ", "NN", "VBG", "IN", "NNP", "NNP", "PRP", "VBP", "NN", ",", "PRP", "VBP", "RB", "VB", "DT", "JJ", "NN", "IN", "NNS", "IN", "DT", "RB", "IN", "CD", "IN", "DT", "NNS", "."], "qSentId": 62, "question": "What?", "question_pos_tagged": ["WP", "."], "aSentId": 62, "answer": "Those two will be on the other side waiting for you. If you become food, I don't want the only set of keys in the belly of one of those things.", "movie_name": "Feast.dial", "answer_ne_tagged": {}, "question_ne_tagged": {}}, {"speaker1": "BOZO", "speaker2": "HEROINE", "docId": 64, "answer_pos_tagged": ["DT", "NNS", "TO", "VB", "IN", "DT", "NN", "IN", "PRP", "."], "qSentId": 63, "question": "Don't get your hopes up.", "question_pos_tagged": ["NNP", "RB", "VB", "PRP$", "NNS", "IN", "."], "aSentId": 63, "answer": "Any volunteers to head into the basement with me?", "movie_name": "Feast.dial", "answer_ne_tagged": {}, "question_ne_tagged": {}}, {"speaker1": "BOZO", "speaker2": "SECOND FLOOR", "docId": 64, "answer_pos_tagged": ["NNP", "NNS", "NNP", "NNP", "NN", "NNS", "CC", "NNS", "."], "qSentId": 64, "question": "Just keep 'em handy, ladies.", "question_pos_tagged": ["RB", "VBP", "JJ", "NN", ",", "NNS", "."], "aSentId": 64, "answer": "Bozo hustles in. The door shuts and locks.", "movie_name": "Feast.dial", "answer_ne_tagged": {}, "question_ne_tagged": {}}, {"speaker1": "BOZO", "speaker2": "SECOND FLOOR", "docId": 64, "answer_pos_tagged": ["NNP", "NNS", "CC", "RB", "NNS", "DT", "JJ", "NN", "."], "qSentId": 65, "question": "Wish me luck... I'm okay! I'm okay!", "question_pos_tagged": ["JJ", "PRP", "VBP", ":", "PRP", "VBP", "JJ", ".", "PRP", "VBP", "JJ", "."], "aSentId": 65, "answer": "Bozo rises and nervously surveys the damaged floor.", "movie_name": "Feast.dial", "answer_ne_tagged": {}, "question_ne_tagged": {}}, {"speaker1": "BELLE", "speaker2": "BOSS MAN", "docId": 64, "answer_pos_tagged": ["NNP", ":"], "qSentId": 67, "question": "How are you holding up?", "question_pos_tagged": ["WRB", "VBP", "PRP", "VBG", "RP", "."], "aSentId": 67, "answer": "Well...", "movie_name": "Feast.dial", "answer_ne_tagged": {}, "question_ne_tagged": {}}, {"speaker1": "BELLE", "speaker2": "BOSS MAN", "docId": 64, "answer_pos_tagged": ["NNP", "NNP", "NN", "NNP", "PRP", "VBP", "DT", "JJ", "NNP", "NNP", "MD", "VB", "DT", "RB", ",", "PRP", "MD", "VB", "PRP$", "NNP", "NNP", "IN", "DT", "NN", "."], "qSentId": 68, "question": "What is this?", "question_pos_tagged": ["WP", "VBZ", "DT", "."], "aSentId": 68, "answer": "Morphine. My magic potion. I need a few drops. You should try a little, it'll calm your nerves. Works like a charm.", "movie_name": "Feast.dial", "answer_ne_tagged": {}, "question_ne_tagged": {}}, {"speaker1": "BELLE", "speaker2": "BOSS MAN", "docId": 64, "answer_pos_tagged": ["NN", ",", "IN", "PRP", "VBP", "DT", ",", "NN", "PRP", "NNP", "NNP", "POS", "DT", "JJ", "NN", "IN", "DT", "NN", "WRB", "PRP", "MD", "VB", "RP", "."], "qSentId": 69, "question": "No other time than now, right?", "question_pos_tagged": ["DT", "JJ", "NN", "IN", "RB", ",", "RB", "."], "aSentId": 69, "answer": "Wait, before you do that, help me move. There's a small room off the kitchen where I can lay down.", "movie_name": "Feast.dial", "answer_ne_tagged": {}, "question_ne_tagged": {}}, {"speaker1": "BELLE", "speaker2": "BOSS MAN", "docId": 64, "answer_pos_tagged": ["PRP", "VBZ", "JJ", "NN", "IN", "NNP", "NNP", "PRP", "."], "qSentId": 70, "question": "But --", "question_pos_tagged": ["CC", ":"], "aSentId": 70, "answer": "It's much safer in there. Trust me.", "movie_name": "Feast.dial", "answer_ne_tagged": {}, "question_ne_tagged": {}}, {"speaker1": "BELLE", "speaker2": "BOSS MAN", "docId": 64, "answer_pos_tagged": ["PRP", "MD", "RB", "VB", "DT", "NN", ",", "NNP", "."], "qSentId": 71, "question": "Doesn't your foot hurt?", "question_pos_tagged": ["VBZ", "RB", "PRP$", "NN", "NN", "."], "aSentId": 71, "answer": "I can't feel a thing, Hon.", "movie_name": "Feast.dial", "answer_ne_tagged": {"LOCATION": ["Hon."]}, "question_ne_tagged": {}}, {"speaker1": "BELLE", "speaker2": "BOSS MAN", "docId": 64, "answer_pos_tagged": ["PRP", "VBP", "DT", "JJ", "NN", ",", "VBP", "RB", "PRP", "."], "qSentId": 72, "question": "How 'bout now?", "question_pos_tagged": ["WRB", "JJ", "RB", "."], "aSentId": 72, "answer": "You're a bad girl, aren't you.", "movie_name": "Feast.dial", "answer_ne_tagged": {}, "question_ne_tagged": {}}, {"speaker1": "BELLE", "speaker2": "BOSS MAN", "docId": 64, "answer_pos_tagged": ["DT", "NN", "POS", "NN", "NNP", "NNP", "PRP", "VBZ", "."], "qSentId": 73, "question": "Um-hmmm.", "question_pos_tagged": ["NN", "."], "aSentId": 73, "answer": "The girl's got rhythm. There it is.", "movie_name": "Feast.dial", "answer_ne_tagged": {}, "question_ne_tagged": {}}, {"speaker1": "HEROINE", "speaker2": "TUFFY", "docId": 64, "answer_pos_tagged": ["NNP", "RB", "VB", ",", "PRP", "VBP", "NNP", "NNP", "."], "qSentId": 74, "question": "Let's get everything upstairs. I'm sorry.", "question_pos_tagged": ["NNP", "POS", "NN", "NN", "NNP", "PRP", "VBP", "JJ", "."], "aSentId": 74, "answer": "Don't worry, I'm fine. Really.", "movie_name": "Feast.dial", "answer_ne_tagged": {}, "question_ne_tagged": {}}, {"speaker1": "HEROINE", "speaker2": "TUFFY", "docId": 64, "answer_pos_tagged": ["NNP", "PRP", ",", "PRP", "VBP", "IN", "VBG", "DT", "JJ", "NN", "WRB", "DT", "VBZ", "IN", ",", "CC", "IN", "RB", ",", "PRP", "DT", "VBP", "TO", "VB", "JJ", ",", "RB", "."], "qSentId": 75, "question": "I admire your strength.", "question_pos_tagged": ["PRP", "VBP", "PRP$", "NN", "."], "aSentId": 75, "answer": "Trust me, I plan on having a full breakdown when this is over, but for now, we all have to be strong, right?", "movie_name": "Feast.dial", "answer_ne_tagged": {}, "question_ne_tagged": {}}, {"speaker1": "HEROINE", "speaker2": "TUFFY", "docId": 64, "answer_pos_tagged": ["UH", ":"], "qSentId": 76, "question": "This is my daughter, Charlie. She's all I'm after.", "question_pos_tagged": ["DT", "VBZ", "PRP$", "NN", ",", "NNP", "NNP", "POS", "DT", "PRP", "VBP", "IN", "."], "aSentId": 76, "answer": "Oh...", "movie_name": "Feast.dial", "answer_ne_tagged": {}, "question_ne_tagged": {}}, {"speaker1": "HEROINE", "speaker2": "TUFFY", "docId": 64, "answer_pos_tagged": ["PRP", "VBP", "PRP", "."], "qSentId": 77, "question": "And I'm gonna need your strength, every bit of it.", "question_pos_tagged": ["CC", "PRP", "VBP", "JJ", "NN", "NN", "PRP$", "NN", ",", "DT", "NN", "IN", "PRP", "."], "aSentId": 77, "answer": "You have it.", "movie_name": "Feast.dial", "answer_ne_tagged": {}, "question_ne_tagged": {}}, {"speaker1": "HEROINE", "speaker2": "TUFFY", "docId": 64, "answer_pos_tagged": ["NNP", "PRP", "."], "qSentId": 78, "question": "Good. But still do me a favor.", "question_pos_tagged": ["NNP", "CC", "RB", "VBP", "PRP", "DT", "NN", "."], "aSentId": 78, "answer": "Name it.", "movie_name": "Feast.dial", "answer_ne_tagged": {}, "question_ne_tagged": {}}, {"speaker1": "HEROINE", "speaker2": "TUFFY", "docId": 64, "answer_pos_tagged": ["NNP", "."], "qSentId": 79, "question": "Don't tell anyone I have a soft side.", "question_pos_tagged": ["NNP", "RB", "VB", "NN", "PRP", "VBP", "DT", "JJ", "NN", "."], "aSentId": 79, "answer": "Deal.", "movie_name": "Feast.dial", "answer_ne_tagged": {}, "question_ne_tagged": {}}, {"speaker1": "BELLE", "speaker2": "BOSS MAN", "docId": 64, "answer_pos_tagged": ["NNP", "NN", "."], "qSentId": 80, "question": "You wanna see, baby?", "question_pos_tagged": ["PRP", "VBD", "NNS", "VBP", ",", "NN", "."], "aSentId": 80, "answer": "Hell yeah.", "movie_name": "Feast.dial", "answer_ne_tagged": {}, "question_ne_tagged": {}}, {"speaker1": "BELLE", "speaker2": "BOSS MAN", "docId": 64, "answer_pos_tagged": ["WRB", "JJ", "PRP", "VBD", ",", "WP", "."], "qSentId": 81, "question": "How much you got?", "question_pos_tagged": ["WRB", "JJ", "PRP", "VBD", "."], "aSentId": 81, "answer": "How much I got, what?", "movie_name": "Feast.dial", "answer_ne_tagged": {}, "question_ne_tagged": {}}, {"speaker1": "BELLE", "speaker2": "BOSS MAN", "docId": 64, "answer_pos_tagged": ["PRP", "VBP", "RB", "VB", ",", "NNP", "NNP", "VBZ", "RB", "NNP", "NNP", "VBZ", "DT", "NN", "IN", "NNP", "CC", "PRP", "VBP", "VB", "NNS", "IN", "VBG", "NN", "IN", "DT", "NN", "IN", "DT", "."], "qSentId": 82, "question": "How much you got to see the show?", "question_pos_tagged": ["WRB", "JJ", "PRP", "VBD", "TO", "VB", "DT", "NN", "."], "aSentId": 82, "answer": "You don't understand, sweety. Daddy doesn't pay. Daddy sees the show for free. But you do get points for being horny on a night like this.", "movie_name": "Feast.dial", "answer_ne_tagged": {}, "question_ne_tagged": {}}, {"speaker1": "BELLE", "speaker2": "BOSS MAN", "docId": 64, "answer_pos_tagged": ["PRP", "MD", "RB", "VB", "DT", "NN", "TO", "VB", "DT", "NN", "IN", "DT", "NN", "NN", "RB", ",", "MD", "PRP", "."], "qSentId": 83, "question": "What?", "question_pos_tagged": ["WP", "."], "aSentId": 83, "answer": "You can't expect a man to buy a car without a test drive first, can you?", "movie_name": "Feast.dial", "answer_ne_tagged": {}, "question_ne_tagged": {}}, {"speaker1": "BELLE", "speaker2": "BOSS MAN", "docId": 64, "answer_pos_tagged": ["RB", "VBP", "IN", "JJ", "JJ", "NN", "IN", "RB", "CC", "NN", "IN", "NNP", "POS", "NN", ",", "PRP", "VBP", "NNS", "VBP", "DT", "VBG", "."], "qSentId": 84, "question": "Um, hmm --", "question_pos_tagged": ["NNP", ",", "NN", ":"], "aSentId": 84, "answer": "Now wiggle that sweet little ass over here and sit on Daddy's face, I wanna do some appraising.", "movie_name": "Feast.dial", "answer_ne_tagged": {}, "question_ne_tagged": {}}, {"speaker1": "HEROINE", "speaker2": "BOSS MAN", "docId": 64, "answer_pos_tagged": ["WP", "."], "qSentId": 85, "question": "What?", "question_pos_tagged": ["WP", "."], "aSentId": 85, "answer": "What?", "movie_name": "Feast.dial", "answer_ne_tagged": {}, "question_ne_tagged": {}}, {"speaker1": "HEROINE", "speaker2": "BOSS MAN", "docId": 64, "answer_pos_tagged": ["PRP", "VBP", "RB", "VB", "NN", "."], "qSentId": 86, "question": "You know what.", "question_pos_tagged": ["PRP", "VBP", "WP", "."], "aSentId": 86, "answer": "I don't know shit.", "movie_name": "Feast.dial", "answer_ne_tagged": {}, "question_ne_tagged": {}}, {"speaker1": "HEROINE", "speaker2": "BOSS MAN", "docId": 64, "answer_pos_tagged": ["NN", ",", "NN", ",", "NN", "."], "qSentId": 87, "question": "You. What was that door downstairs?", "question_pos_tagged": ["NNP", "WP", "VBD", "IN", "NN", "NNS", "."], "aSentId": 87, "answer": "Wait, wait, wait.", "movie_name": "Feast.dial", "answer_ne_tagged": {}, "question_ne_tagged": {}}, {"speaker1": "HEROINE", "speaker2": "BOSS MAN", "docId": 64, "answer_pos_tagged": ["NNP", ",", "NNP", "PRP", "VBP", "RB", "IN", "EX", "."], "qSentId": 89, "question": "What's it for? What's it for!?", "question_pos_tagged": ["WP", "VBZ", "PRP", "IN", ".", "WP", "VBZ", "PRP", "IN", ".", "."], "aSentId": 89, "answer": "Grass, man. I grow pot down there.", "movie_name": "Feast.dial", "answer_ne_tagged": {}, "question_ne_tagged": {}}, {"speaker1": "HEROINE", "speaker2": "BOSS MAN", "docId": 64, "answer_pos_tagged": ["PRP", "VBZ", "RP", "IN", "DT", "NN", "NNP", "NNP", "NN", "VBZ", "IN", ",", "CC", "PRP", "VBP", "RB", "RB", "JJ", "RB", "TO", "VB", "DT", "JJ", "NN", "."], "qSentId": 90, "question": "Does the tunnel spit out near a car?", "question_pos_tagged": ["VBZ", "DT", "NN", "NN", "IN", "IN", "DT", "NN", "."], "aSentId": 90, "answer": "It spits out behind the parking lot. My truck is near, but it ain't nearly big enough to haul the whole lot.", "movie_name": "Feast.dial", "answer_ne_tagged": {}, "question_ne_tagged": {}}, {"speaker1": "HEROINE", "speaker2": "BOSS MAN", "docId": 64, "answer_pos_tagged": ["RB", "."], "qSentId": 91, "question": "It's a shot. Is it gassed up?", "question_pos_tagged": ["PRP", "VBZ", "DT", "NNP", "NNP", "PRP", "VBD", "RP", "."], "aSentId": 91, "answer": "Fully.", "movie_name": "Feast.dial", "answer_ne_tagged": {}, "question_ne_tagged": {}}, {"speaker1": "HEROINE", "speaker2": "BOSS MAN", "docId": 64, "answer_pos_tagged": ["CD", "."], "qSentId": 92, "question": "Four door?", "question_pos_tagged": ["CD", "NN", "."], "aSentId": 92, "answer": "Two.", "movie_name": "Feast.dial", "answer_ne_tagged": {}, "question_ne_tagged": {}}, {"speaker1": "HEROINE", "speaker2": "BOSS MAN", "docId": 64, "answer_pos_tagged": ["CD", "."], "qSentId": 93, "question": "How many can it hold?", "question_pos_tagged": ["WRB", "JJ", "MD", "PRP", "VB", "."], "aSentId": 93, "answer": "Six.", "movie_name": "Feast.dial", "answer_ne_tagged": {}, "question_ne_tagged": {}}, {"speaker1": "HEROINE", "speaker2": "BOSS MAN", "docId": 64, "answer_pos_tagged": ["CD", "."], "qSentId": 94, "question": "Max?", "question_pos_tagged": ["NNP", "."], "aSentId": 94, "answer": "Seven.", "movie_name": "Feast.dial", "answer_ne_tagged": {}, "question_ne_tagged": {}}, {"speaker1": "HEROINE", "speaker2": "BOSS MAN", "docId": 64, "answer_pos_tagged": ["NNP", "VBZ", "MD", "RB", "VB", "."], "qSentId": 95, "question": "It's gonna fit thirteen.", "question_pos_tagged": ["PRP", "VBZ", "NN", "NN", "NN", "NN", "."], "aSentId": 95, "answer": "Thirteen clowns wouldn't fit.", "movie_name": "Feast.dial", "answer_ne_tagged": {}, "question_ne_tagged": {}}, {"speaker1": "TRAMPY", "speaker2": "ADULTERER", "docId": 64, "answer_pos_tagged": ["NNP", "."], "qSentId": 97, "question": "How does it feel?", "question_pos_tagged": ["WRB", "VBZ", "PRP", "VB", "."], "aSentId": 97, "answer": "Lousy.", "movie_name": "Feast.dial", "answer_ne_tagged": {}, "question_ne_tagged": {}}, {"speaker1": "TRAMPY", "speaker2": "ADULTERER", "docId": 64, "answer_pos_tagged": ["NNS", ",", "DT", "NN", "VBG", "."], "qSentId": 98, "question": "You still have one left.", "question_pos_tagged": ["PRP", "RB", "VBP", "CD", "VBN", "."], "aSentId": 98, "answer": "Yes, the silver lining.", "movie_name": "Feast.dial", "answer_ne_tagged": {}, "question_ne_tagged": {}}, {"speaker1": "TRAMPY", "speaker2": "ADULTERER", "docId": 64, "answer_pos_tagged": ["NNP", "PRP", "."], "qSentId": 99, "question": "It serves you right for cheating.", "question_pos_tagged": ["PRP", "VBZ", "PRP", "RB", "IN", "NN", "."], "aSentId": 99, "answer": "Spare me.", "movie_name": "Feast.dial", "answer_ne_tagged": {}, "question_ne_tagged": {}}, {"speaker1": "TRAMPY", "speaker2": "BOZO", "docId": 64, "answer_pos_tagged": ["UH", "NN", "."], "qSentId": 101, "question": "I figure it's karma. You wronged me and you wronged your wife, so this is karma biting you on the ass, or in your case... in the eye.", "question_pos_tagged": ["PRP", "VBP", "PRP", "VBZ", "NNP", "NNP", "VBD", "PRP", "CC", "PRP", "VBD", "PRP$", "NN", ",", "RB", "DT", "VBZ", "NN", "VBG", "PRP", "IN", "DT", "NN", ",", "CC", "IN", "PRP$", "NN", ":", "IN", "DT", "NN", "."], "aSentId": 101, "answer": "Oh yeah?", "movie_name": "Feast.dial", "answer_ne_tagged": {}, "question_ne_tagged": {}}, {"speaker1": "TRAMPY", "speaker2": "BOZO", "docId": 64, "answer_pos_tagged": ["NNP", "VBP", ",", "IN", "POS", "RB", "DT", "JJ", "NN", "IN", "NNP", "NNP", "CD", ",", "CC", "RB", "NNP", "PRP", "MD", "VB", "PRP", "RP", "."], "qSentId": 102, "question": "It could be worse, you could be dead. Then again, the climax is upon us.", "question_pos_tagged": ["PRP", "MD", "VB", "JJ", ",", "PRP", "MD", "VB", "NNP", "NNP", "RB", ",", "DT", "NN", "VBZ", "IN", "PRP", "."], "aSentId": 102, "answer": "Ya know, that's not a bad look on you. Kinda 1985, but not bad. I'd hook it up.", "movie_name": "Feast.dial", "answer_ne_tagged": {"DATE": ["1985"]}, "question_ne_tagged": {}}, {"speaker1": "TRAMPY", "speaker2": "BOZO", "docId": 64, "answer_pos_tagged": ["NN", "."], "qSentId": 103, "question": "I wouldn't fuck you for practice.", "question_pos_tagged": ["PRP", "MD", "RB", "VB", "PRP", "IN", "NN", "."], "aSentId": 103, "answer": "Tease.", "movie_name": "Feast.dial", "answer_ne_tagged": {}, "question_ne_tagged": {}}, {"speaker1": "ROADIE", "speaker2": "HEROINE", "docId": 64, "answer_pos_tagged": ["NNP", "NNP", "DT", "NN", "."], "qSentId": 104, "question": "You handle yourself pretty well. You a cop or a criminal?", "question_pos_tagged": ["PRP", "VBP", "PRP", "RB", "NNP", "NNP", "DT", "NN", "CC", "DT", "JJ", "."], "aSentId": 104, "answer": "Neither. Just a farmer.", "movie_name": "Feast.dial", "answer_ne_tagged": {}, "question_ne_tagged": {}}, {"speaker1": "ROADIE", "speaker2": "HEROINE", "docId": 64, "answer_pos_tagged": ["PRP", "RB", "VBP", "IN", "PRP$", "NN", "CC", "NN", ":", "CC", "DT", "NN", "VBZ", "NNP", "NNP", "."], "qSentId": 105, "question": "Oh yeah? Then how do you do it?", "question_pos_tagged": ["UH", "NN", ".", "RB", "WRB", "VBP", "PRP", "VB", "PRP", "."], "aSentId": 105, "answer": "I just think about my husband and daughter... and the rest is easy. Easy.", "movie_name": "Feast.dial", "answer_ne_tagged": {}, "question_ne_tagged": {}}, {"speaker1": "BOZO", "speaker2": "BEER GUY", "docId": 64, "answer_pos_tagged": ["WP", "VBP", "PRP", "VB", "."], "qSentId": 107, "question": "Ah-ah-ah! You're doing that all wrong!", "question_pos_tagged": ["JJ", "NN", "PRP", "VBP", "VBG", "IN", "DT", "JJ", "."], "aSentId": 107, "answer": "What do you know?", "movie_name": "Feast.dial", "answer_ne_tagged": {}, "question_ne_tagged": {}}, {"speaker1": "BOZO", "speaker2": "BEER GUY", "docId": 64, "answer_pos_tagged": ["NNP", "PRP", "."], "qSentId": 108, "question": "I know you're doing it wrong.", "question_pos_tagged": ["PRP", "VBP", "PRP", "VBP", "VBG", "PRP", "JJ", "."], "aSentId": 108, "answer": "Prove it.", "movie_name": "Feast.dial", "answer_ne_tagged": {}, "question_ne_tagged": {}}, {"speaker1": "HEROINE", "speaker2": "BOSS MAN", "docId": 64, "answer_pos_tagged": ["NNP", "IN", "PRP", "VBP", "PRP", ",", "PRP", "VBP", "JJ", "NN", "RB", "NN", "RB", "RB", ",", "NN", "IN", "NN", ",", "RB", "VBP", "IN", "IN", "IN", "RB", "."], "qSentId": 110, "question": "Let's prepare ourselves, they ought to be here with the truck any minute.", "question_pos_tagged": ["NNP", "POS", "NN", "NNS", ",", "PRP", "MD", "TO", "VB", "RB", "IN", "DT", "NN", "DT", "NN", "."], "aSentId": 110, "answer": "Bullshit. If you ask me, I'm gonna just lay right here, wait for sunrise, then walk on out of here.", "movie_name": "Feast.dial", "answer_ne_tagged": {}, "question_ne_tagged": {}}, {"speaker1": "HEROINE", "speaker2": "BOSS MAN", "docId": 64, "answer_pos_tagged": ["IN", "DT", "IN", "PRP", "VBP", "IN", "PRP", ",", "PRP", "MD", "RB", "VB", "IN", "NN", "NN", "''", "NNP", "NNP", "IN", "DT", "NN", "IN", "NNS", ":", "NNP", ".", ".", "."], "qSentId": 111, "question": "That's your choice, but this is going to get a whole lot worse before it gets any better.", "question_pos_tagged": ["DT", "VBZ", "PRP$", "NN", ",", "CC", "DT", "VBZ", "VBG", "TO", "VB", "DT", "JJ", "NN", "NN", "IN", "PRP", "VBZ", "DT", "JJR", "."], "aSentId": 111, "answer": "If all of you run for it, they won't care about lil ol' me. They like the food that moves... OHHH!!!", "movie_name": "Feast.dial", "answer_ne_tagged": {}, "question_ne_tagged": {}}, {"speaker1": "BOZO", "speaker2": "HEROINE", "docId": 64, "answer_pos_tagged": ["WP", "VBZ", "NNP", "NNP", "."], "qSentId": 113, "question": "Commence Plan B!", "question_pos_tagged": ["NN", "NNP", "NNP", "."], "aSentId": 113, "answer": "What's Plan B?", "movie_name": "Feast.dial", "answer_ne_tagged": {}, "question_ne_tagged": {}}, {"speaker1": "BOZO", "speaker2": "HEROINE", "docId": 64, "answer_pos_tagged": ["RB", "VBP"], "qSentId": 114, "question": "Just watch the floor and keep the others safe! Bomb's away!!!", "question_pos_tagged": ["RB", "VBP", "DT", "NN", "CC", "VB", "DT", "NNS", "VBP", ".", "NNP", "POS", "NN", ".", ".", "."], "aSentId": 114, "answer": "Now!", "movie_name": "Feast.dial", "answer_ne_tagged": {}, "question_ne_tagged": {}}, {"speaker1": "BOZO", "speaker2": "HEROINE", "docId": 64, "answer_pos_tagged": ["NNP", "PRP", ".", "NNP", "IN", "."], "qSentId": 115, "question": "One down, one to go!!!", "question_pos_tagged": ["CD", "IN", ",", "CD", "TO", "VB", ".", ".", "."], "aSentId": 115, "answer": "Help me! Come on!", "movie_name": "Feast.dial", "answer_ne_tagged": {}, "question_ne_tagged": {}}, {"speaker1": "HEROINE", "speaker2": "ADULTERER", "docId": 64, "answer_pos_tagged": ["NNP", ":"], "qSentId": 116, "question": "This place is a ghost town.", "question_pos_tagged": ["DT", "NN", "VBZ", "DT", "NN", "NN", "."], "aSentId": 116, "answer": "Look!", "movie_name": "Feast.dial", "answer_ne_tagged": {}, "question_ne_tagged": {}}, {"speaker1": "HEROINE", "speaker2": "ADULTERER", "docId": 64, "answer_pos_tagged": ["NNP", ":", "EX", "VBZ", "NN", "IN", "."], "qSentId": 117, "question": "Charlie? Charlie!", "question_pos_tagged": ["NNP", ".", "NNP", "."], "aSentId": 117, "answer": "Stop! There's something wrong!", "movie_name": "Feast.dial", "answer_ne_tagged": {}, "question_ne_tagged": {}}]